{
  "schemaVersion": 1,
  "id": "throwablecheese",
  "version": "${version}",
  "name": "[Let's Do Addon] Throwable Cheese",
  "description": "This is an example description! Tell everyone what your mod is about!",
  "authors": [
    "Me!"
  ],
  "contact": {
    "homepage": "https://fabricmc.net/",
    "sources": "https://github.com/FabricMC/fabric-example-mod"
  },
  "license": "CC0-1.0",
  "icon": "assets/throwablecheese/icon.png",
  "environment": "*",
  "entrypoints": {
    "main": [
      "dev.doaddon.throwablecheese.fabric.ThrowableCheeseFabric"
    ],
    "client": [
      "dev.doaddon.throwablecheese.fabric.client.ThrowableCheeseFabricClient"
    ],
    "fabric-datagen": [
      "dev.doaddon.throwablecheese.datagen.ThrowableCheeseDataGeneration"
    ]
  },
  "mixins": [
    "throwablecheese.mixins.json"
  ],
  "depends": {
    "fabricloader": ">=0.15.10",
    "minecraft": "~1.20.1",
    "java": ">=17",
    "architectury": ">=9.2.14",
    "fabric-api": "*"
  },
  "suggests": {
    "another-mod": "*"
  }
}
